cnn_framework/__init__.py
cnn_framework/_version.py
cnn_framework/_tests/__init__.py
cnn_framework/_tests/test_classification.py
cnn_framework/_tests/test_regression.py
cnn_framework/data/__init__.py
cnn_framework/data/tools.py
cnn_framework/dummy_cnn/__init__.py
cnn_framework/dummy_cnn/data_set.py
cnn_framework/dummy_cnn/model.py
cnn_framework/dummy_cnn/model_params.py
cnn_framework/dummy_cnn/test.py
cnn_framework/dummy_cnn/train.py
cnn_framework/dummy_regression_cnn/__init__.py
cnn_framework/dummy_regression_cnn/data_set.py
cnn_framework/dummy_regression_cnn/model.py
cnn_framework/dummy_regression_cnn/model_params.py
cnn_framework/dummy_regression_cnn/test.py
cnn_framework/dummy_regression_cnn/train.py
cnn_framework/dummy_segmentation/__init__.py
cnn_framework/dummy_segmentation/data_set.py
cnn_framework/dummy_segmentation/model.py
cnn_framework/dummy_segmentation/model_params.py
cnn_framework/dummy_segmentation/test.py
cnn_framework/dummy_segmentation/train.py
cnn_framework/dummy_sim_clr/__init__.py
cnn_framework/dummy_sim_clr/data_set.py
cnn_framework/dummy_sim_clr/model.py
cnn_framework/dummy_sim_clr/model_params.py
cnn_framework/dummy_vae_model/__init__.py
cnn_framework/dummy_vae_model/data_set.py
cnn_framework/dummy_vae_model/decoder.py
cnn_framework/dummy_vae_model/encoder.py
cnn_framework/dummy_vae_model/model_params.py
cnn_framework/utils/__init__.py
cnn_framework/utils/create_dummy_data_set.py
cnn_framework/utils/dimensions.py
cnn_framework/utils/display_tools.py
cnn_framework/utils/enum.py
cnn_framework/utils/file_name_encoder.py
cnn_framework/utils/preprocessing.py
cnn_framework/utils/tools.py
cnn_framework/utils/augmentations/clip.py
cnn_framework/utils/augmentations/unnormalize.py
cnn_framework/utils/data_loader_generators/__init__.py
cnn_framework/utils/data_loader_generators/classifier_data_loader_generator.py
cnn_framework/utils/data_loader_generators/data_loader_generator.py
cnn_framework/utils/data_managers/__init__.py
cnn_framework-0.6.0.dist-info/licenses/LICENSE
cnn_framework-0.6.0.dist-info/METADATA
cnn_framework-0.6.0.dist-info/WHEEL
cnn_framework-0.6.0.dist-info/top_level.txt
cnn_framework-0.6.0.dist-info/RECORD
