Metadata-Version: 2.4
Name: cnn_framework
Version: 0.6.0
Summary: CNN framework
Home-page: https://github.com/15bonte/cnn_framework
Author: Thomas Bonte
Author-email: thomas.bonte@mines-paristech.fr
License: BSD-3-Clause
Project-URL: Bug Tracker, https://github.com/15bonte/cnn_detector/issues
Project-URL: Documentation, https://github.com/15bonte/cnn_detector#README.md
Project-URL: Source Code, https://github.com/15bonte/cnn_detector
Project-URL: User Support, https://github.com/15bonte/cnn_detector/issues
Classifier: Programming Language :: Python :: 3.9
Classifier: Programming Language :: Python :: 3.10
Requires-Python: >=3.9
License-File: LICENSE
Requires-Dist: torch>=1.12.1
Requires-Dist: scikit-image>=0.19.3
Requires-Dist: matplotlib
Requires-Dist: scikit-learn>=1.2.2
Requires-Dist: pint>=0.19.2
Requires-Dist: torchvision>=0.13.1
Requires-Dist: albumentations>=1.3.0
Requires-Dist: torchmetrics>=0.11.4
Requires-Dist: big-fish>=0.6.2
Requires-Dist: pillow>=9.2.0
Requires-Dist: segmentation-models-pytorch>=0.3.0
Requires-Dist: protobuf==3.20.*
Requires-Dist: tensorboard>=2.8.0
Requires-Dist: aicsimageio>=4.13.0
Requires-Dist: tensorflow==2.16.2
Provides-Extra: testing
Requires-Dist: tox; extra == "testing"
Requires-Dist: pytest; extra == "testing"
Requires-Dist: pytest-cov; extra == "testing"
Requires-Dist: pytest-qt; extra == "testing"
Requires-Dist: pyqt5; extra == "testing"
Dynamic: license-file
